{"1200":["AU","1200","Sydney","New South Wales","NSW","","","","","-33.8678","151.2073","4"],"1201":["AU","1201","Sydney","New South Wales","NSW","","","","","-33.8678","151.2073","4"],"1202":["AU","1202","Sydney","New South Wales","NSW","","","","","-33.8678","151.2073","4"],"1203":["AU","1203","Sydney","New South Wales","NSW","","","","","-33.8678","151.2073","4"],"1204":["AU","1204","Sydney","New South Wales","NSW","","","","","-33.8678","151.2073","4"],"1205":["AU","1205","Sydney","New South Wales","NSW","","","","","-33.8678","151.2073","4"],"1206":["AU","1206","Sydney","New South Wales","NSW","","","","","-33.8678","151.2073","4"],"1207":["AU","1207","Sydney","New South Wales","NSW","","","","","-33.8678","151.2073","4"],"1208":["AU","1208","Haymarket","New South Wales","NSW","","","","","-33.8787","151.2053","4"],"1209":["AU","1209","Australia Square","New South Wales","NSW","","","","","-33.8691","151.2071","1"],"1210":["AU","1210","Australia Square","New South Wales","NSW","","","","","-33.8707","151.2068","1"],"1211":["AU","1211","Australia Square","New South Wales","NSW","","","","","-33.8707","151.2068","1"],"1212":["AU","1212","Australia Square","New South Wales","NSW","","","","","-33.8707","151.2068","1"],"1213":["AU","1213","Australia Square","New South Wales","NSW","","","","","-33.8707","151.2068","1"],"1214":["AU","1214","Australia Square","New South Wales","NSW","","","","","-33.8707","151.2068","1"],"1215":["AU","1215","Australia Square","New South Wales","NSW","SYDNEY STREETS","","","","-33.8707","151.2068","1"],"1216":["AU","1216","Grosvenor Place","New South Wales","NSW","","","","","-33.8707","151.2068","1"],"1217":["AU","1217","Grosvenor Place","New South Wales","NSW","","","","","-33.8707","151.2068","1"],"1218":["AU","1218","Grosvenor Place","New South Wales","NSW","","","","","-33.8707","151.2068","1"],"1219":["AU","1219","Grosvenor Place","New South Wales","NSW","","","","","-33.8707","151.2068","1"],"1220":["AU","1220","Grosvenor Place","New South Wales","NSW","SYDNEY STREETS","","","","-33.8707","151.2068","1"],"1221":["AU","1221","Royal Exchange","New South Wales","NSW","","","","","-33.8707","151.2068","1"],"1222":["AU","1222","Royal Exchange","New South Wales","NSW","","","","","-33.8707","151.2068","1"],"1223":["AU","1223","Royal Exchange","New South Wales","NSW","","","","","-33.8707","151.2068","1"],"1224":["AU","1224","Royal Exchange","New South Wales","NSW","","","","","-33.8707","151.2068","1"],"1225":["AU","1225","Royal Exchange","New South Wales","NSW","SYDNEY STREETS","","","","-33.8707","151.2068","1"],"1226":["AU","1226","Queen Victoria Building","New South Wales","NSW","","","","","-33.8707","151.2068","1"],"1227":["AU","1227","Queen Victoria Building","New South Wales","NSW","","","","","-33.8707","151.2068","1"],"1228":["AU","1228","Queen Victoria Building","New South Wales","NSW","","","","","-33.8707","151.2068","1"],"1229":["AU","1229","Queen Victoria Building","New South Wales","NSW","","","","","-33.8707","151.2068","1"],"1230":["AU","1230","Queen Victoria Building","New South Wales","NSW","SYDNEY STREETS","","","","-33.8787","151.2053","1"],"1231":["AU","1231","Sydney South","New South Wales","NSW","","","","","-33.8787","151.2053","1"],"1232":["AU","1232","Sydney South","New South Wales","NSW","","","","","-33.8787","151.2053","1"],"1233":["AU","1233","Sydney South","New South Wales","NSW","","","","","-33.8787","151.2053","1"],"1234":["AU","1234","Sydney South","New South Wales","NSW","","","","","-33.8787","151.2053","1"],"1235":["AU","1235","Sydney South","New South Wales","NSW","SYDNEY STREETS","","","","-33.8787","151.2053","1"],"1236":["AU","1236","Haymarket","New South Wales","NSW","","","","","-33.8787","151.2053","4"],"1237":["AU","1237","Haymarket","New South Wales","NSW","","","","","-33.8787","151.2053","4"],"1238":["AU","1238","Haymarket","New South Wales","NSW","","","","","-33.8787","151.2053","4"],"1239":["AU","1239","Haymarket","New South Wales","NSW","","","","","-33.8787","151.2053","4"],"1240":["AU","1240","Haymarket","New South Wales","NSW","SYDNEY STREETS","","","","-33.8787","151.2053","4"],"1291":["AU","1291","Sydney","New South Wales","NSW","","","","","-33.8678","151.2073","4"],"1292":["AU","1292","Sydney","New South Wales","NSW","","","","","-33.8678","151.2073","4"],"1293":["AU","1293","Sydney","New South Wales","NSW","","","","","-33.8678","151.2073","4"],"1294":["AU","1294","Sydney","New South Wales","NSW","","","","","-33.8678","151.2073","4"],"1295":["AU","1295","Sydney","New South Wales","NSW","","","","","-33.8678","151.2073","4"],"1296":["AU","1296","Sydney","New South Wales","NSW","","","","","-33.8678","151.2073","4"],"1297":["AU","1297","Sydney","New South Wales","NSW","","","","","-33.8678","151.2073","4"],"1298":["AU","1298","Sydney","New South Wales","NSW","","","","","-33.8678","151.2073","4"],"1299":["AU","1299","Sydney","New South Wales","NSW","","","","","-33.8678","151.2073","4"]}